nougat/__init__.py
nougat/app.py
nougat/asgi.py
nougat/config.py
nougat/exceptions.py
nougat/test_client.py
nougat/utils.py
nougat/context/__init__.py
nougat/context/request.py
nougat/context/response.py
nougat-0.3.2.dist-info/METADATA
nougat-0.3.2.dist-info/RECORD
nougat-0.3.2.dist-info/WHEEL
nougat-0.3.2.dist-info/top_level.txt
