Metadata-Version: 2.1
Name: nougat
Version: 0.3.2
Summary: Async web framework
Home-page: https://github.com/Kilerd/nougat
Author: Kilerd Chan
License: MIT
Keywords: web framework async
Platform: UNKNOWN
Classifier: Development Status :: 3 - Alpha
Classifier: Intended Audience :: Developers
Classifier: Environment :: Web Environment
Classifier: License :: OSI Approved :: MIT License
Classifier: Programming Language :: Python :: 3.6
Requires-Python: >=3.6
Requires-Dist: aiohttp
Requires-Dist: httptools
Requires-Dist: yarl (>=0.13.0)
Requires-Dist: websockets
